src/probstat_package_Slighting6397/__init__.py
src/probstat_package_Slighting6397/probstat.py
probstat-0.0.1.dist-info/METADATA
probstat-0.0.1.dist-info/WHEEL
probstat-0.0.1.dist-info/licenses/LICENSE
probstat-0.0.1.dist-info/RECORD
